CHANGES.txt
LICENSE.txt
README.txt
buildout.cfg
setup.py
src/getpaid/__init__.py
src/getpaid.report.egg-info/PKG-INFO
src/getpaid.report.egg-info/SOURCES.txt
src/getpaid.report.egg-info/dependency_links.txt
src/getpaid.report.egg-info/entry_points.txt
src/getpaid.report.egg-info/namespace_packages.txt
src/getpaid.report.egg-info/not-zip-safe
src/getpaid.report.egg-info/requires.txt
src/getpaid.report.egg-info/top_level.txt
src/getpaid/report/__init__.py
src/getpaid/report/configure.zcml
src/getpaid/report/domain.py
src/getpaid/report/i18n.py
src/getpaid/report/profiles.zcml
src/getpaid/report/readme.txt
src/getpaid/report/report.py
src/getpaid/report/schema.py
src/getpaid/report/session.py
src/getpaid/report/subscriber.py
src/getpaid/report/sync.py
src/getpaid/report/tests.py
src/getpaid/report/browser/__init__.py
src/getpaid/report/browser/backorder.pt
src/getpaid/report/browser/backorder.py
src/getpaid/report/browser/configure.zcml
src/getpaid/report/browser/fulfillment.pt
src/getpaid/report/browser/fulfillment.py
src/getpaid/report/browser/history.pt
src/getpaid/report/browser/history.py
src/getpaid/report/browser/report-listing.pt
src/getpaid/report/profiles/default/actions.xml