Metadata-Version: 1.0
Name: getpaid.report
Version: 0.1.1
Summary: Relational Reports For getpaid.core.
Home-page: http://code.google.com/p/getpaid
Author: Kapil Thangavelu
Author-email: kapil.foss@gmail.com
License: X11
Keywords: zope zope3
Platform: UNKNOWN
